{
  "experiment_id": "hnsw_ranker-seed42-20260712T141802",
  "generated_at": "2026-07-12T14:18:02",
  "tool": "simulate (ReelRank Phase 4 evaluation harness)",
  "git": {
    "reel_rank_sha": "56a13d41bc98b0733b4bbf71a2df30e2a58c3eb6",
    "reel_rank_dir": "/Users/derranw/reel-rank",
    "reel_rank_dirty": true,
    "vector_db_sha": "17e434a3e741f702ffb8e0f00b0484676d988198",
    "vector_db_dir": "/Users/derranw/vector-db"
  },
  "build": {
    "type": "Release",
    "compiler": "AppleClang 21.0.0.21000101",
    "cxx_standard": 20
  },
  "hardware": {
    "cpu_model": "Apple M5",
    "logical_cores": 10,
    "physical_cores": 10,
    "ram_bytes": 25769803776
  },
  "os": {
    "sysname": "Darwin",
    "release": "25.5.0",
    "version": "Darwin Kernel Version 25.5.0: Mon Apr 27 20:39:29 PDT 2026; root:xnu-12377.121.6~2/RELEASE_ARM64_T8142",
    "machine": "arm64"
  },
  "execution": {
    "threads_used": 1,
    "note": "single-threaded simulation core (D13)"
  },
  "dataset": {
    "users": 10000,
    "reels": 100000,
    "creators": 5000,
    "topics": 32,
    "dimensions": 64
  }
}
